hellobye/__init__.py
hellobye/hellobye.py
hellobye-0.0.1.dist-info/LICENSE
hellobye-0.0.1.dist-info/METADATA
hellobye-0.0.1.dist-info/WHEEL
hellobye-0.0.1.dist-info/top_level.txt
hellobye-0.0.1.dist-info/RECORD
