Metadata-Version: 2.1
Name: hellobye
Version: 0.0.1
Summary: It says "Hello" and "Bye".
Home-page: http://hellobye.c1.biz
Author: Tymoteusz Moryto
Author-email: tymek24m@gmail.com
License: UNKNOWN
Platform: UNKNOWN
Classifier: Programming Language :: Python :: 3
Classifier: License :: OSI Approved :: MIT License
Classifier: Operating System :: OS Independent
